LICENSE
README.md
setup.py
alegra/__init__.py
alegra/client.py
alegra/exceptions.py
alegra_python.egg-info/PKG-INFO
alegra_python.egg-info/SOURCES.txt
alegra_python.egg-info/dependency_links.txt
alegra_python.egg-info/not-zip-safe
alegra_python.egg-info/requires.txt
alegra_python.egg-info/top_level.txt