Metadata-Version: 2.1
Name: alegra-python
Version: 0.1.0
Summary: API wrapper for Alegra written in Python
Home-page: https://github.com/GearPlug/alegra-python
Author: Juan Carlos Rios
Author-email: juankrios15@gmail.com
License: MIT
License-File: LICENSE
